[
    {
        "title": "How I got hooked on economics",
        "time": "00:04:53.600",
        "title_prob": -1.0022614002227783
    },
    {
        "title": "How do you handle the dichotomy between means and ends?",
        "time": "00:17:50.440",
        "title_prob": -0.6232060790061951
    },
    {
        "title": "Why the market analogy breaks down in schooling",
        "time": "00:20:47.640",
        "title_prob": -0.6428535580635071
    },
    {
        "title": "India's 'wrong means' in education",
        "time": "00:28:43.080",
        "title_prob": -0.8680208921432495
    },
    {
        "title": "Why India's private sector is'schizophrenic'",
        "time": "00:32:20.000",
        "title_prob": -0.5782732367515564
    },
    {
        "title": "What has been wrong with public schooling?",
        "time": "00:36:44.760",
        "title_prob": -0.6054438948631287
    },
    {
        "title": "Is profit a dirty word?",
        "time": "00:38:10.720",
        "title_prob": -0.6660892963409424
    },
    {
        "title": "Why India should be obsessed with poverty, not inequality",
        "time": "00:42:25.520",
        "title_prob": -0.6570023894309998
    },
    {
        "title": "Nehru: Poverty is good, inequality is bad",
        "time": "00:46:02.400",
        "title_prob": -0.805659294128418
    },
    {
        "title": "Karthik Muralidharan on the PPE of Indian Education",
        "time": "00:51:36.960",
        "title_prob": -0.4372751712799072
    },
    {
        "title": "Why is India's education system failing?",
        "time": "00:57:36.360",
        "title_prob": -0.7760754823684692
    },
    {
        "title": "Why India's Education Spending Is Not Translating Into Outcomes",
        "time": "01:03:54.480",
        "title_prob": -0.4392578601837158
    },
    {
        "title": "What is the role of research in India's education?",
        "time": "01:38:28.560",
        "title_prob": -0.9041767716407776
    },
    {
        "title": "Rajan's take on the new education policy",
        "time": "01:44:04.560",
        "title_prob": -0.8106788992881775
    },
    {
        "title": "Why the sanctimonious left is wrong about the NEP",
        "time": "01:53:02.560",
        "title_prob": -0.9043048620223999
    },
    {
        "title": "Why we need to get rid of democracy",
        "time": "01:55:13.560",
        "title_prob": -0.9206912517547607
    },
    {
        "title": "Is the National Education Policy a step in the right direction?",
        "time": "01:57:46.560",
        "title_prob": -0.49670836329460144
    },
    {
        "title": "How do you design a sea change?",
        "time": "02:03:55.560",
        "title_prob": -0.8728440999984741
    },
    {
        "title": "Is India's National Action Plan a good policy document?",
        "time": "02:05:07.560",
        "title_prob": -0.8586008548736572
    },
    {
        "title": "What would you do if you were in charge?",
        "time": "02:10:03.560",
        "title_prob": -0.4435337781906128
    },
    {
        "title": "Cost Effectiveness of School Complexes in India",
        "time": "02:22:29.560",
        "title_prob": -0.6870225667953491
    },
    {
        "title": "How to get better outcomes for primary education if you hire buses rather than build schools",
        "time": "02:28:57.560",
        "title_prob": -0.7753292322158813
    },
    {
        "title": "Why India needs an episode in federalism",
        "time": "02:30:04.560",
        "title_prob": -0.6980262994766235
    },
    {
        "title": "Why a teacher apprenticeship is a win-win-win for the public sector in India",
        "time": "02:31:34.560",
        "title_prob": -0.8656234741210938
    },
    {
        "title": "What stands in the way of something like this happening?",
        "time": "02:41:38.200",
        "title_prob": -0.5278778672218323
    },
    {
        "title": "Private schools and school vouchers in India",
        "time": "02:44:59.200",
        "title_prob": -0.895447850227356
    },
    {
        "title": "Is Private Schooling Better Than Public Schooling?",
        "time": "02:48:22.200",
        "title_prob": -0.7226032614707947
    },
    {
        "title": "Is it better to send your kid to a private school or a government school?",
        "time": "02:56:13.320",
        "title_prob": -0.6242223978042603
    },
    {
        "title": "Should the government have a say in language?",
        "time": "02:57:54.320",
        "title_prob": -0.5200228095054626
    },
    {
        "title": "India's education system is an authoritarian system",
        "time": "03:00:32.920",
        "title_prob": -0.6801150441169739
    },
    {
        "title": "Let's talk about regulation of private schools in India",
        "time": "03:02:42.160",
        "title_prob": -0.9442134499549866
    },
    {
        "title": "How do you harness the creative energies of the private sector?",
        "time": "03:04:00.720",
        "title_prob": -0.554628312587738
    },
    {
        "title": "What keeps you going? What's your private juice?",
        "time": "03:11:57.880",
        "title_prob": -0.7681548595428467
    },
    {
        "title": "Why I think I have the best job in the world",
        "time": "03:13:40.920",
        "title_prob": -0.38131582736968994
    }
]