[
    {
        "title": "I dreamed that I died and went to heaven",
        "time": "00:00:00.000",
        "title_prob": -0.6279399394989014
    },
    {
        "title": "Why did India nationalize banks?",
        "time": "00:03:25.560",
        "title_prob": -0.6934962272644043
    },
    {
        "title": "Indira Gandhi's 'Garibi Hata'",
        "time": "00:06:08.160",
        "title_prob": -0.7496727705001831
    },
    {
        "title": "India's Public Sector Banks: How Effective Are They?",
        "time": "00:07:00.360",
        "title_prob": -0.8337642550468445
    },
    {
        "title": "Private banks do better than public sector banks in achieving priority sector lending criteria",
        "time": "00:08:26.160",
        "title_prob": -0.6625951528549194
    },
    {
        "title": "Why public sector banks fail",
        "time": "00:10:28.560",
        "title_prob": -0.7851468920707703
    },
    {
        "title": "Perverse incentives in the banking system",
        "time": "00:12:54.560",
        "title_prob": -0.7913389801979065
    },
    {
        "title": "Why aren't banks open to competition?",
        "time": "00:14:44.960",
        "title_prob": -0.8370961546897888
    },
    {
        "title": "Is privatization of public sector banks a good idea?",
        "time": "00:15:58.760",
        "title_prob": -0.6711977124214172
    },
    {
        "title": "Why do public sector banks have higher NPAs?",
        "time": "00:18:57.360",
        "title_prob": -0.5101990699768066
    },
    {
        "title": "India's NPA crisis: How bad is it for the economy?",
        "time": "00:24:49.160",
        "title_prob": -0.9458314180374146
    },
    {
        "title": "Why India's banking system was not affected by the global financial crisis",
        "time": "00:26:28.960",
        "title_prob": -0.7916972041130066
    },
    {
        "title": "Why public sector banks are a victim of their own success",
        "time": "00:27:43.760",
        "title_prob": -0.8363952040672302
    },
    {
        "title": "Why the NPA problem is the flip side of the public sector bank problem",
        "time": "00:29:26.160",
        "title_prob": -0.8322571516036987
    }
]